Metadata-Version: 2.4
Name: django-uwsgi-ng
Version: 2.0.4
Summary: uWSGI stuff for Django projects
Home-page: https://edugit.org/AlekSIS/libs/django-uwsgi-ng
Author: Eugene MechanisM
Author-email: eugene@mechanism.pro
Maintainer: Dominik George
Maintainer-email: dominik.george@teckids.org
License: MIT
Keywords: uwsgi,django,mail,cache,template
Classifier: Development Status :: 4 - Beta
Classifier: Framework :: Django
Classifier: Intended Audience :: Developers
Classifier: Intended Audience :: System Administrators
Classifier: License :: OSI Approved :: MIT License
Classifier: Operating System :: OS Independent
Classifier: Programming Language :: Python
Classifier: Programming Language :: Python :: 3.7
Classifier: Framework :: Django
Classifier: Framework :: Django :: 3.0
Classifier: Framework :: Django :: 4.0
Classifier: Topic :: Software Development :: Libraries :: Python Modules
Classifier: Topic :: Internet :: WWW/HTTP :: WSGI
Classifier: Topic :: Internet :: WWW/HTTP :: WSGI :: Application
Classifier: Topic :: Internet :: WWW/HTTP :: Dynamic Content
Classifier: Topic :: Internet :: WWW/HTTP :: Site Management
Classifier: Topic :: Software Development :: Build Tools
Classifier: Topic :: Software Development :: Code Generators
Classifier: Topic :: Communications :: Email
Classifier: Framework :: Django
License-File: LICENSE
Provides-Extra: uwsgi
Requires-Dist: uwsgi; extra == "uwsgi"
Dynamic: author
Dynamic: author-email
Dynamic: classifier
Dynamic: description
Dynamic: home-page
Dynamic: keywords
Dynamic: license
Dynamic: license-file
Dynamic: maintainer
Dynamic: maintainer-email
Dynamic: provides-extra
Dynamic: summary
